soft_nudge/__init__.py
soft_nudge/animation_caching.py
soft_nudge/baking.py
soft_nudge/cpu_utils.py
soft_nudge/cuda_utils.py
soft_nudge/soft_nudge.py
soft_nudge/soft_nudge_cpu.py
soft_nudge/soft_nudge_cuda.py
soft_nudge/utils.py
soft_nudge/baked_animation_data_processors/__init__.py
soft_nudge/baked_animation_data_processors/data_processor_stencil_format.py
soft_nudge/baked_animation_data_processors/data_processors.py
soft_nudge-1.5.0.dist-info/METADATA
soft_nudge-1.5.0.dist-info/WHEEL
soft_nudge-1.5.0.dist-info/licenses/LICENSE
soft_nudge-1.5.0.dist-info/RECORD
