Metadata-Version: 2.1
Name: soft_nudge
Version: 1.5.0
Summary: A non invasive timer to give you a soft nudge in the right direction.
Project-URL: Homepage, https://github.com/80sVectorz/soft_nudge
Project-URL: Bug Tracker, https://github.com/80sVectorz/soft_nudge/issues
Author: 80sVectorz
License-File: LICENSE
Classifier: License :: OSI Approved :: GNU General Public License v3 (GPLv3)
Classifier: Operating System :: Microsoft :: Windows
Classifier: Programming Language :: Python :: 3
Requires-Python: >=3.8
Requires-Dist: cuda-python
Requires-Dist: numba
Requires-Dist: numpy
Requires-Dist: pywin32
Requires-Dist: wxpython
